wallpaper/__init__.py
wallpaper/__version__.py
wallpaper/mac.py
wallpaper/wallpaper.py
wallpaper/win.py
py_wallpaper-0.1.0.dist-info/LICENSE
py_wallpaper-0.1.0.dist-info/METADATA
py_wallpaper-0.1.0.dist-info/WHEEL
py_wallpaper-0.1.0.dist-info/top_level.txt
py_wallpaper-0.1.0.dist-info/RECORD
