Metadata-Version: 2.1
Name: py-wallpaper
Version: 0.1.0
Summary: Python wallpaper for Humans.
Home-page: https://www.leetao94.cn
Author: Leetao
Author-email: leetao94cn@gmail.com
License: Apache 2.0
Platform: UNKNOWN
Requires-Python: >=3.0.*
